{
    "executionRoleArn": "arn:aws:iam::452911533244:role/ecsTaskExecutionRole",
    "containerDefinitions": [
        {
            "portMappings": [
                {
                    "hostPort": 9080,
                    "protocol": "tcp",
                    "containerPort": 9080
                }
            ],
            "image": "452911533244.dkr.ecr.us-west-2.amazonaws.com/myapp:v1.0.0",
            "essential": true,
            "name": "java-azul-verde-container"
        }
    ],
    "memory": "512",
    "compatibilities": [
        "EC2",
        "FARGATE"
    ],
    "family": "get-azul-verde-task",
    "requiresCompatibilities": [
        "FARGATE"
    ],
    "networkMode": "awsvpc",
    "cpu": "256"
}
